waveform_reg_access_extractor/__init__.py
waveform_reg_access_extractor/__main__.py
waveform_reg_access_extractor/cli.py
waveform_reg_access_extractor/config/__init__.py
waveform_reg_access_extractor/config/signal_mapping.py
waveform_reg_access_extractor/decoders/__init__.py
waveform_reg_access_extractor/decoders/transaction_decoder.py
waveform_reg_access_extractor/parsers/__init__.py
waveform_reg_access_extractor/parsers/base_parser.py
waveform_reg_access_extractor/parsers/vcd_parser.py
waveform_reg_access_extractor/protocols/__init__.py
waveform_reg_access_extractor/protocols/ahb.py
waveform_reg_access_extractor/protocols/apb.py
waveform_reg_access_extractor/protocols/base_protocol.py
waveform_reg_access_extractor/register_maps/__init__.py
waveform_reg_access_extractor/register_maps/base_register_map.py
waveform_reg_access_extractor/register_maps/ipxact.py
waveform_reg_access_extractor/register_maps/yaml.py
waveform_reg_access_extractor/utils/__init__.py
waveform_reg_access_extractor/utils/file_utils.py
waveform_reg_access_extractor/utils/logging_config.py
waveform_reg_access_extractor-0.1.0.0.dist-info/licenses/LICENSE
waveform_reg_access_extractor-0.1.0.0.dist-info/METADATA
waveform_reg_access_extractor-0.1.0.0.dist-info/WHEEL
waveform_reg_access_extractor-0.1.0.0.dist-info/entry_points.txt
waveform_reg_access_extractor-0.1.0.0.dist-info/top_level.txt
waveform_reg_access_extractor-0.1.0.0.dist-info/RECORD
